contas/admin.py
contas/apps.py
contas/models.py
contas/permissions.py
contas/serializers.py
contas/tests.py
contas/urls.py
contas/views.py
contas/__init__.py
contas/migrations/0001_initial.py
contas/migrations/0002_conta_owner.py
contas/migrations/__init__.py
contas_api/settings.py
contas_api/tests.py
contas_api/urls.py
contas_api/wsgi.py
contas_api/__init__.py
contas_api_temp-0.1.dist-info/DESCRIPTION.rst
contas_api_temp-0.1.dist-info/METADATA
contas_api_temp-0.1.dist-info/metadata.json
contas_api_temp-0.1.dist-info/RECORD
contas_api_temp-0.1.dist-info/top_level.txt
contas_api_temp-0.1.dist-info/WHEEL
lancamentos/admin.py
lancamentos/apps.py
lancamentos/models.py
lancamentos/pagination.py
lancamentos/permissions.py
lancamentos/serializers.py
lancamentos/tests.py
lancamentos/urls.py
lancamentos/views.py
lancamentos/__init__.py
lancamentos/migrations/0001_initial.py
lancamentos/migrations/__init__.py
usuarios/admin.py
usuarios/apps.py
usuarios/permissions.py
usuarios/serializers.py
usuarios/tests.py
usuarios/urls.py
usuarios/views.py
usuarios/__init__.py
usuarios/migrations/__init__.py
